cpu_count/__init__.py
cpu_count/cpu_count.py
cpu_count/monkey_patch.py
cpu_count/py.typed
cpu_count-1.0.0.dist-info/LICENSE
cpu_count-1.0.0.dist-info/METADATA
cpu_count-1.0.0.dist-info/WHEEL
cpu_count-1.0.0.dist-info/eager_resources.txt
cpu_count-1.0.0.dist-info/top_level.txt
cpu_count-1.0.0.dist-info/zip-safe
cpu_count-1.0.0.dist-info/RECORD
