Metadata-Version: 2.1
Name: cpu_count
Version: 1.0.0
Summary: Calculate the number of CPUs available taking into account system constraints
Home-page: https://github.com/HeavenVolkoff/cpu_count
Author: Vítor Vasconcellos
Author-email: vasconcellos.dev@gmail.com
Maintainer: Vítor Vasconcellos
Maintainer-email: vasconcellos.dev@gmail.com
License: BSD-3-Clause
Project-URL: Bug Tracker, https://github.com/HeavenVolkoff/cpu_count/issues
Project-URL: Source Code, https://github.com/HeavenVolkoff/cpu_count
Keywords: base,modules,package,bootstrap,foundation
Platform: UNKNOWN
Classifier: Development Status :: 4 - Beta
Classifier: Intended Audience :: Developers
Classifier: Intended Audience :: System Administrators
Classifier: Programming Language :: Python :: 3 :: Only
Classifier: Programming Language :: Python :: 3.5
Classifier: Programming Language :: Python :: 3.6
Classifier: Programming Language :: Python :: 3.7
Classifier: Programming Language :: Python :: 3.8
Classifier: Programming Language :: Python :: 3.9
Requires-Python: >3.5
Provides-Extra: dev
Provides-Extra: docs
Provides-Extra: tests
